bpl_lib/__init__.py
bpl_lib/address/Address.py
bpl_lib/address/__init__.py
bpl_lib/crypto/Crypto.py
bpl_lib/crypto/Keys.py
bpl_lib/crypto/Signature.py
bpl_lib/crypto/__init__.py
bpl_lib/helpers/Constants.py
bpl_lib/helpers/Database.py
bpl_lib/helpers/Exceptions.py
bpl_lib/helpers/Util.py
bpl_lib/helpers/__init__.py
bpl_lib/network/DDL.py
bpl_lib/network/Network.py
bpl_lib/network/__init__.py
bpl_lib/time/Time.py
bpl_lib/time/__init__.py
bpl_lib/transactions/Delegate.py
bpl_lib/transactions/IPFS.py
bpl_lib/transactions/MultiSignature.py
bpl_lib/transactions/SecondSignature.py
bpl_lib/transactions/Transaction.py
bpl_lib/transactions/Transfer.py
bpl_lib/transactions/Vote.py
bpl_lib/transactions/__init__.py
bpl_lib-0.1.0.dist-info/METADATA
bpl_lib-0.1.0.dist-info/RECORD
bpl_lib-0.1.0.dist-info/WHEEL
bpl_lib-0.1.0.dist-info/top_level.txt
