Metadata-Version: 2.1
Name: bpl-lib
Version: 0.1.0
Summary: A library for the Blockpool Blockchain.
Home-page: https://github.com/DuneRoot/bpl-lib
Author: Alistair O'Brien
Author-email: alistair.o'brien@ellesmere.com
License: UNKNOWN
Platform: UNKNOWN
Requires-Dist: base58 (>=1.0.0)
Requires-Dist: ecdsa
